TwoVariableRelation.py
TwoVariableRelation-0.2.dist-info/LICENSE.txt
TwoVariableRelation-0.2.dist-info/METADATA
TwoVariableRelation-0.2.dist-info/WHEEL
TwoVariableRelation-0.2.dist-info/top_level.txt
TwoVariableRelation-0.2.dist-info/RECORD
