Metadata-Version: 2.1
Name: TwoVariableRelation
Version: 0.2
Summary: TwoVariableRelation Package is intended to establish the relationship between two features of the dataset.
Home-page: UNKNOWN
Author: Aanal Shah,Shalini
License: UNKNOWN
Platform: UNKNOWN
Classifier: Programming Language :: Python :: 3
Classifier: License :: OSI Approved :: MIT License
Requires-Python: >=3.6
License-File: LICENSE.txt
